feapson/__init__.py
feapson/decoder.py
feapson/encoder.py
feapson/scanner.py
feapson/tool.py
feapson-1.0.0.dist-info/LICENSE
feapson-1.0.0.dist-info/METADATA
feapson-1.0.0.dist-info/WHEEL
feapson-1.0.0.dist-info/top_level.txt
feapson-1.0.0.dist-info/RECORD
