Metadata-Version: 2.1
Name: feapson
Version: 1.0.0
Summary: Same as json.dumps or json.loads, feapson supprot feapson.dumps and feapson.loads
Home-page: https://github.com/Boris-code/feapson.git
Author: Boris
Author-email: boris_liu@foxmail.com
License: MIT
Platform: UNKNOWN
Classifier: Programming Language :: Python :: 3
Requires-Python: >=3
License-File: LICENSE
